{
    "id": 7,
    "label": 1048070,
    "description": 1048071,
    "option": [
        {
            "app": 73,
            "action": [
                {
                    "command": "delete",
                    "search": "walk.files",
                    "path": "~/.Trash"
                },
                {
                    "command": "delete",
                    "search": "walk.all",
                    "path": "~/.local/share/Trash/files"
                },
                {
                    "command": "delete",
                    "search": "walk.all",
                    "path": "~/.local/share/Trash/info"
                },
                {
                    "command": "delete",
                    "search": "walk.all",
                    "path": "~/.local/share/Trash/expunged"
                }
            ]
        }
    ]
}